captcha_solver/__init__.py
captcha_solver_selenium-0.2.9.dist-info/METADATA
captcha_solver_selenium-0.2.9.dist-info/WHEEL
captcha_solver_selenium-0.2.9.dist-info/top_level.txt
captcha_solver_selenium-0.2.9.dist-info/RECORD
