Metadata-Version: 2.2
Name: captcha_solver_selenium
Version: 0.2.9
Summary: A package for solving Google reCAPTCHA using Selenium and Speech Recognition
Author: DENO
Author-email: Vinhytb3010@gmail.com
Classifier: Programming Language :: Python :: 3
Classifier: License :: OSI Approved :: MIT License
Classifier: Operating System :: OS Independent
Requires-Python: >=3.10
Requires-Dist: selenium>=4.9.1
Requires-Dist: selenium-wire>=5.0.0
Requires-Dist: requests>=2.31.0
Requires-Dist: SpeechRecognition
Requires-Dist: pyaudio
Requires-Dist: pydub==0.25.1
Requires-Dist: blinker==1.7.0
Requires-Dist: setuptools
Dynamic: author
Dynamic: author-email
Dynamic: classifier
Dynamic: description
Dynamic: description-content-type
Dynamic: requires-dist
Dynamic: requires-python
Dynamic: summary
